xbcli/__init__.py
xbcli/__version__.py
xbcli/cli_util.py
xbcli/py.typed
xbcli-0.1.27.dist-info/LICENSE
xbcli-0.1.27.dist-info/METADATA
xbcli-0.1.27.dist-info/WHEEL
xbcli-0.1.27.dist-info/top_level.txt
xbcli-0.1.27.dist-info/RECORD
