Metadata-Version: 2.1
Name: xbcli
Version: 0.1.27
Summary: A simple tools for flask_cli
Home-page: https://xiangbei-tech.com/
Author: Sun Bo
Author-email: sunboemail@sina.com
License: MIT
Classifier: License :: OSI Approved :: MIT License
Classifier: Programming Language :: Python
Classifier: Programming Language :: Python :: 3
Classifier: Programming Language :: Python :: Implementation :: CPython
Requires-Python: >=3.10
License-File: LICENSE
Requires-Dist: flask
Requires-Dist: click
Provides-Extra: support_mypy
Requires-Dist: types-setuptools; extra == "support-mypy"
